flocky/__init__.py
flocky/_modidx.py
flocky/api.py
flocky/core.py
flocky-0.0.2.dist-info/licenses/LICENSE
flocky-0.0.2.dist-info/METADATA
flocky-0.0.2.dist-info/WHEEL
flocky-0.0.2.dist-info/entry_points.txt
flocky-0.0.2.dist-info/top_level.txt
flocky-0.0.2.dist-info/RECORD
