Metadata-Version: 2.4
Name: flocky
Version: 0.0.2
Summary: (Unofficial) SDK for Flock.io
Home-page: https://github.com/CarloLepelaars/flocky
Author: Carlo Lepelaars
Author-email: info@carlolepelaars.nl
License: Apache Software License 2.0
Keywords: flockio llm
Classifier: Development Status :: 4 - Beta
Classifier: Intended Audience :: Developers
Classifier: Natural Language :: English
Classifier: Programming Language :: Python :: 3.10
Classifier: Programming Language :: Python :: 3.11
Classifier: Programming Language :: Python :: 3.12
Classifier: License :: OSI Approved :: Apache Software License
Requires-Python: >=3.10
License-File: LICENSE
Requires-Dist: fastcore
Requires-Dist: fastprogress
Requires-Dist: python-fasthtml
Requires-Dist: python-dotenv
Requires-Dist: pandas
Requires-Dist: huggingface-hub
Requires-Dist: torch<2.7,>=1.10
Provides-Extra: dev
Dynamic: author
Dynamic: author-email
Dynamic: classifier
Dynamic: description
Dynamic: description-content-type
Dynamic: home-page
Dynamic: keywords
Dynamic: license
Dynamic: license-file
Dynamic: provides-extra
Dynamic: requires-dist
Dynamic: requires-python
Dynamic: summary
